circuit-rbm/AIS.py
circuit-rbm/__init__.py
circuit-rbm/autoencoder.py
circuit-rbm/circuit_utils.py
circuit-rbm/convolutional_rbm.py
circuit-rbm/rbm.py
circuit-rbm/rbm_celeb.py
circuit-rbm/rbm_collectivefilter_pytorch.py
circuit-rbm/rbm_pytorch.py
circuit-rbm/utils_pytorch.py
rkm/AIS.py
rkm/__init__.py
rkm/autoencoder.py
rkm/circuit_utils.py
rkm/convolutional_rbm.py
rkm/rbm.py
rkm/rbm_celeb.py
rkm/rbm_collectivefilter_pytorch.py
rkm/rbm_pytorch.py
rkm/utils_pytorch.py
circuit_rbm-0.0.17.dist-info/METADATA
circuit_rbm-0.0.17.dist-info/WHEEL
circuit_rbm-0.0.17.dist-info/top_level.txt
circuit_rbm-0.0.17.dist-info/RECORD
